{"20": {"0": {"idx": 0, "max": 0.09169, "counts": 344}, "1800": {"idx": 1, "max": 0.09051, "counts": 608}, "3600": {"idx": 2, "max": 0.13032, "counts": 938}, "5400": {"idx": 3, "max": 0.09707, "counts": 1483}, "7200": {"idx": 4, "max": 0.75578, "counts": 1943}, "9000": {"idx": 5, "max": 0.86555, "counts": 2402}, "10800": {"idx": 6, "max": 0.62979, "counts": 2555}, "12600": {"idx": 7, "max": 0.49961, "counts": 2803}, "14400": {"idx": 8, "max": 0.49578, "counts": 2164}, "16200": {"idx": 9, "max": 0.49902, "counts": 1633}, "18000": {"idx": 10, "max": 0.26367, "counts": 1490}, "19800": {"idx": 11, "max": 0.46603, "counts": 1770}, "21600": {"idx": 12, "max": 0.40471, "counts": 2367}, "23400": {"idx": 13, "max": 0.5367, "counts": 2370}, "25200": {"idx": 14, "max": 0.32968, "counts": 1680}, "27000": {"idx": 15, "max": 0.1334, "counts": 1231}, "28800": {"idx": 16, "max": 0.13638, "counts": 1114}, "30600": {"idx": 17, "max": 0.19925, "counts": 1038}, "32400": {"idx": 18, "max": 0.19922, "counts": 1017}, "34200": {"idx": 19, "max": 0.09986, "counts": 913}, "36000": {"idx": 20, "max": 0.07472, "counts": 603}, "37800": {"idx": 21, "max": 0.0417, "counts": 499}, "39600": {"idx": 22, "max": 0.05631, "counts": 524}, "41400": {"idx": 23, "max": 0.06049, "counts": 470}, "43200": {"idx": 24, "max": 0.04539, "counts": 543}, "45000": {"idx": 25, "max": 0.06747, "counts": 715}, "46800": {"idx": 26, "max": 0.12686, "counts": 713}, "48600": {"idx": 27, "max": 0.10907, "counts": 748}, "50400": {"idx": 28, "max": 0.14122, "counts": 798}, "52200": {"idx": 29, "max": 0.15506, "counts": 913}, "54000": {"idx": 30, "max": 0.17297, "counts": 1021}, "55800": {"idx": 31, "max": 0.21679, "counts": 1097}, "57600": {"idx": 32, "max": 0.43319, "counts": 1234}, "59400": {"idx": 33, "max": 0.29762, "counts": 1314}, "61200": {"idx": 34, "max": 0.30662, "counts": 1515}, "63000": {"idx": 35, "max": 0.43483, "counts": 1742}, "64800": {"idx": 36, "max": 0.55806, "counts": 1962}, "66600": {"idx": 37, "max": 0.63614, "counts": 2333}, "68400": {"idx": 38, "max": 1.57823, "counts": 2764}, "70200": {"idx": 39, "max": 2.41233, "counts": 3170}, "72000": {"idx": 40, "max": 2.04732, "counts": 3292}, "73800": {"idx": 41, "max": 1.70335, "counts": 3403}, "75600": {"idx": 42, "max": 1.13669, "counts": 3623}, "77400": {"idx": 43, "max": 0.91959, "counts": 3791}, "79200": {"idx": 44, "max": 1.12008, "counts": 3848}, "81000": {"idx": 45, "max": 1.30411, "counts": 3975}, "82800": {"idx": 46, "max": 1.10204, "counts": 3981}, "84600": {"idx": 47, "max": 1.12141, "counts": 3998}, "86400": {"idx": 48, "max": 1.33981, "counts": 4000}, "88200": {"idx": 49, "max": 1.73776, "counts": 4062}, "90000": {"idx": 50, "max": 1.54563, "counts": 4174}, "91800": {"idx": 51, "max": 1.18238, "counts": 4332}, "93600": {"idx": 52, "max": 0.92877, "counts": 4479}, "95400": {"idx": 53, "max": 0.81539, "counts": 4566}, "97200": {"idx": 54, "max": 0.78336, "counts": 4836}, "99000": {"idx": 55, "max": 0.7393, "counts": 5001}, "100800": {"idx": 56, "max": 0.67982, "counts": 4956}, "102600": {"idx": 57, "max": 1.12635, "counts": 7183}, "104400": {"idx": 58, "max": 1.55034, "counts": 7541}, "106200": {"idx": 59, "max": 1.2851, "counts": 7254}, "108000": {"idx": 60, "max": 1.23972, "counts": 6619}, "109800": {"idx": 61, "max": 1.01336, "counts": 5878}, "111600": {"idx": 62, "max": 1.26259, "counts": 5469}, "113400": {"idx": 63, "max": 0.71663, "counts": 5021}, "115200": {"idx": 64, "max": 0.49225, "counts": 4547}, "117000": {"idx": 65, "max": 0.44854, "counts": 3916}, "118800": {"idx": 66, "max": 0.38273, "counts": 3604}, "120600": {"idx": 67, "max": 0.35057, "counts": 3360}, "122400": {"idx": 68, "max": 0.25473, "counts": 3148}, "124200": {"idx": 69, "max": 0.21918, "counts": 3042}, "126000": {"idx": 70, "max": 0.22598, "counts": 2896}, "127800": {"idx": 71, "max": 0.25467, "counts": 2858}, "129600": {"idx": 72, "max": 0.41055, "counts": 2750}, "131400": {"idx": 73, "max": 0.1792, "counts": 2704}, "133200": {"idx": 74, "max": 0.28176, "counts": 2822}, "135000": {"idx": 75, "max": 0.23795, "counts": 2997}, "136800": {"idx": 76, "max": 0.37781, "counts": 3276}, "138600": {"idx": 77, "max": 0.60478, "counts": 3789}, "140400": {"idx": 78, "max": 0.71326, "counts": 4186}, "142200": {"idx": 79, "max": 0.67651, "counts": 4543}, "144000": {"idx": 80, "max": 0.89394, "counts": 5068}, "145800": {"idx": 81, "max": 1.61603, "counts": 5542}, "147600": {"idx": 82, "max": 1.27931, "counts": 6022}, "149400": {"idx": 83, "max": 1.68881, "counts": 6347}, "151200": {"idx": 84, "max": 1.98077, "counts": 6608}, "153000": {"idx": 85, "max": 1.53774, "counts": 6761}, "154800": {"idx": 86, "max": 2.49123, "counts": 7154}, "156600": {"idx": 87, "max": 3.0746, "counts": 7428}, "158400": {"idx": 88, "max": 2.72247, "counts": 7416}, "160200": {"idx": 89, "max": 2.11425, "counts": 7914}, "162000": {"idx": 90, "max": 1.93855, "counts": 8377}, "163800": {"idx": 91, "max": 1.42044, "counts": 8816}, "165600": {"idx": 92, "max": 1.35579, "counts": 8763}, "167400": {"idx": 93, "max": 1.13783, "counts": 8495}, "169200": {"idx": 94, "max": 0.97197, "counts": 8323}, "171000": {"idx": 95, "max": 1.22979, "counts": 8308}, "172800": {"idx": 96, "max": 3.39163, "counts": 8458}, "174600": {"idx": 97, "max": 2.13476, "counts": 8649}, "176400": {"idx": 98, "max": 3.4337, "counts": 9263}, "178200": {"idx": 99, "max": 2.2619, "counts": 9659}, "180000": {"idx": 100, "max": 2.77474, "counts": 9876}, "181800": {"idx": 101, "max": 3.61036, "counts": 9946}, "183600": {"idx": 102, "max": 1.8739, "counts": 9441}, "185400": {"idx": 103, "max": 1.21061, "counts": 8213}, "187200": {"idx": 104, "max": 1.19431, "counts": 7770}, "189000": {"idx": 105, "max": 1.28935, "counts": 7400}, "190800": {"idx": 106, "max": 1.56771, "counts": 7010}, "192600": {"idx": 107, "max": 0.74368, "counts": 6285}, "194400": {"idx": 108, "max": 0.7084, "counts": 5659}, "196200": {"idx": 109, "max": 0.42018, "counts": 4873}, "198000": {"idx": 110, "max": 0.80513, "counts": 4506}, "199800": {"idx": 111, "max": 0.56147, "counts": 4279}, "201600": {"idx": 112, "max": 0.46129, "counts": 4042}, "203400": {"idx": 113, "max": 0.57991, "counts": 4039}, "205200": {"idx": 114, "max": 0.57112, "counts": 3696}, "207000": {"idx": 115, "max": 0.2704, "counts": 3308}, "208800": {"idx": 116, "max": 0.38904, "counts": 3161}, "210600": {"idx": 117, "max": 0.29958, "counts": 3065}, "212400": {"idx": 118, "max": 0.37019, "counts": 2931}, "214200": {"idx": 119, "max": 0.40635, "counts": 2848}, "216000": {"idx": 120, "max": 0.33576, "counts": 2623}, "217800": {"idx": 121, "max": 0.33302, "counts": 2544}, "219600": {"idx": 122, "max": 0.28095, "counts": 2584}, "221400": {"idx": 123, "max": 0.26295, "counts": 2594}, "223200": {"idx": 124, "max": 0.27196, "counts": 2644}, "225000": {"idx": 125, "max": 0.42431, "counts": 2774}, "226800": {"idx": 126, "max": 0.47154, "counts": 2847}, "228600": {"idx": 127, "max": 0.45204, "counts": 3080}, "230400": {"idx": 128, "max": 0.568, "counts": 3218}, "232200": {"idx": 129, "max": 0.56677, "counts": 3541}, "234000": {"idx": 130, "max": 0.66772, "counts": 3868}, "235800": {"idx": 131, "max": 0.57286, "counts": 4359}, "237600": {"idx": 132, "max": 1.45885, "counts": 4599}, "239400": {"idx": 133, "max": 1.6327, "counts": 4817}, "241200": {"idx": 134, "max": 1.38051, "counts": 4982}, "243000": {"idx": 135, "max": 1.64926, "counts": 5034}, "244800": {"idx": 136, "max": 2.04503, "counts": 5164}, "246600": {"idx": 137, "max": 1.73361, "counts": 5255}, "248400": {"idx": 138, "max": 3.40322, "counts": 5691}, "250200": {"idx": 139, "max": 1.79115, "counts": 5452}, "252000": {"idx": 140, "max": 1.14357, "counts": 5501}, "253800": {"idx": 141, "max": 1.51574, "counts": 5829}, "255600": {"idx": 142, "max": 1.04676, "counts": 5820}, "257400": {"idx": 143, "max": 1.20273, "counts": 5589}, "259200": {"idx": 144, "max": 0.0, "counts": 0}}}