{"281": {"0": {"idx": 0, "max": 0.10464, "counts": 315}, "1800": {"idx": 1, "max": 0.09429, "counts": 579}, "3600": {"idx": 2, "max": 0.14464, "counts": 839}, "5400": {"idx": 3, "max": 0.08674, "counts": 1227}, "7200": {"idx": 4, "max": 0.17739, "counts": 1588}, "9000": {"idx": 5, "max": 0.70188, "counts": 1922}, "10800": {"idx": 6, "max": 0.60754, "counts": 2333}, "12600": {"idx": 7, "max": 0.8176, "counts": 2608}, "14400": {"idx": 8, "max": 0.6274, "counts": 1926}, "16200": {"idx": 9, "max": 0.36698, "counts": 1530}, "18000": {"idx": 10, "max": 0.2951, "counts": 1339}, "19800": {"idx": 11, "max": 0.33293, "counts": 1590}, "21600": {"idx": 12, "max": 0.42286, "counts": 2072}, "23400": {"idx": 13, "max": 0.3049, "counts": 2051}, "25200": {"idx": 14, "max": 0.29375, "counts": 1370}, "27000": {"idx": 15, "max": 0.12581, "counts": 1126}, "28800": {"idx": 16, "max": 0.12155, "counts": 1065}, "30600": {"idx": 17, "max": 0.0993, "counts": 985}, "32400": {"idx": 18, "max": 0.11883, "counts": 997}, "34200": {"idx": 19, "max": 0.25209, "counts": 969}, "36000": {"idx": 20, "max": 0.12891, "counts": 610}, "37800": {"idx": 21, "max": 0.07682, "counts": 588}, "39600": {"idx": 22, "max": 0.08436, "counts": 608}, "41400": {"idx": 23, "max": 0.12674, "counts": 624}, "43200": {"idx": 24, "max": 0.06485, "counts": 623}, "45000": {"idx": 25, "max": 0.13543, "counts": 939}, "46800": {"idx": 26, "max": 0.17581, "counts": 1026}, "48600": {"idx": 27, "max": 0.25578, "counts": 1094}, "50400": {"idx": 28, "max": 0.24638, "counts": 1020}, "52200": {"idx": 29, "max": 0.17539, "counts": 1027}, "54000": {"idx": 30, "max": 0.27572, "counts": 1110}, "55800": {"idx": 31, "max": 0.46827, "counts": 1305}, "57600": {"idx": 32, "max": 0.42758, "counts": 1379}, "59400": {"idx": 33, "max": 0.48491, "counts": 1488}, "61200": {"idx": 34, "max": 0.43636, "counts": 1554}, "63000": {"idx": 35, "max": 0.38222, "counts": 1678}, "64800": {"idx": 36, "max": 0.64718, "counts": 1764}, "66600": {"idx": 37, "max": 0.75698, "counts": 1881}, "68400": {"idx": 38, "max": 0.93931, "counts": 2103}, "70200": {"idx": 39, "max": 1.20697, "counts": 2326}, "72000": {"idx": 40, "max": 1.17913, "counts": 2470}, "73800": {"idx": 41, "max": 1.86241, "counts": 2632}, "75600": {"idx": 42, "max": 2.63913, "counts": 2921}, "77400": {"idx": 43, "max": 2.17668, "counts": 2921}, "79200": {"idx": 44, "max": 2.00062, "counts": 2943}, "81000": {"idx": 45, "max": 2.09557, "counts": 3049}, "82800": {"idx": 46, "max": 2.50396, "counts": 3478}, "84600": {"idx": 47, "max": 2.42917, "counts": 3482}, "86400": {"idx": 48, "max": 2.46962, "counts": 3603}, "88200": {"idx": 49, "max": 2.60062, "counts": 3660}, "90000": {"idx": 50, "max": 3.04152, "counts": 3745}, "91800": {"idx": 51, "max": 3.0685, "counts": 4050}, "93600": {"idx": 52, "max": 3.52457, "counts": 4107}, "95400": {"idx": 53, "max": 3.73873, "counts": 4024}, "97200": {"idx": 54, "max": 3.82876, "counts": 3864}, "99000": {"idx": 55, "max": 3.16964, "counts": 3927}, "100800": {"idx": 56, "max": 3.02123, "counts": 4030}, "102600": {"idx": 57, "max": 3.76164, "counts": 5977}, "104400": {"idx": 58, "max": 3.30525, "counts": 6255}, "106200": {"idx": 59, "max": 3.18019, "counts": 6041}, "108000": {"idx": 60, "max": 2.77678, "counts": 5678}, "109800": {"idx": 61, "max": 2.10238, "counts": 4959}, "111600": {"idx": 62, "max": 1.4685, "counts": 4384}, "113400": {"idx": 63, "max": 1.2224, "counts": 4142}, "115200": {"idx": 64, "max": 0.97608, "counts": 3898}, "117000": {"idx": 65, "max": 0.74949, "counts": 3431}, "118800": {"idx": 66, "max": 0.64299, "counts": 3290}, "120600": {"idx": 67, "max": 0.38946, "counts": 2925}, "122400": {"idx": 68, "max": 0.51264, "counts": 2805}, "124200": {"idx": 69, "max": 0.49859, "counts": 2721}, "126000": {"idx": 70, "max": 0.55684, "counts": 2785}, "127800": {"idx": 71, "max": 0.49145, "counts": 2696}, "129600": {"idx": 72, "max": 0.58938, "counts": 2659}, "131400": {"idx": 73, "max": 0.62778, "counts": 2468}, "133200": {"idx": 74, "max": 0.7045, "counts": 2475}, "135000": {"idx": 75, "max": 0.66736, "counts": 2483}, "136800": {"idx": 76, "max": 0.82987, "counts": 2744}, "138600": {"idx": 77, "max": 0.80193, "counts": 2959}, "140400": {"idx": 78, "max": 1.22361, "counts": 3175}, "142200": {"idx": 79, "max": 1.08226, "counts": 3438}, "144000": {"idx": 80, "max": 1.13025, "counts": 3698}, "145800": {"idx": 81, "max": 1.41044, "counts": 4010}, "147600": {"idx": 82, "max": 1.08435, "counts": 4144}, "149400": {"idx": 83, "max": 1.73063, "counts": 4422}, "151200": {"idx": 84, "max": 2.01786, "counts": 4738}, "153000": {"idx": 85, "max": 1.62468, "counts": 4924}, "154800": {"idx": 86, "max": 1.65807, "counts": 5185}, "156600": {"idx": 87, "max": 1.94085, "counts": 5268}, "158400": {"idx": 88, "max": 2.10684, "counts": 5294}, "160200": {"idx": 89, "max": 1.70804, "counts": 5355}, "162000": {"idx": 90, "max": 1.70628, "counts": 5577}, "163800": {"idx": 91, "max": 2.01603, "counts": 5737}, "165600": {"idx": 92, "max": 1.91575, "counts": 5806}, "167400": {"idx": 93, "max": 1.86536, "counts": 5852}, "169200": {"idx": 94, "max": 1.86408, "counts": 5730}, "171000": {"idx": 95, "max": 1.9972, "counts": 5622}, "172800": {"idx": 96, "max": 2.2359, "counts": 5574}, "174600": {"idx": 97, "max": 1.69758, "counts": 5817}, "176400": {"idx": 98, "max": 1.98274, "counts": 5656}, "178200": {"idx": 99, "max": 1.6333, "counts": 6000}, "180000": {"idx": 100, "max": 1.99203, "counts": 6312}, "181800": {"idx": 101, "max": 1.99349, "counts": 5993}, "183600": {"idx": 102, "max": 1.82213, "counts": 5818}, "185400": {"idx": 103, "max": 1.20258, "counts": 5217}, "187200": {"idx": 104, "max": 2.2973, "counts": 5499}, "189000": {"idx": 105, "max": 1.67591, "counts": 5068}, "190800": {"idx": 106, "max": 1.02519, "counts": 4637}, "192600": {"idx": 107, "max": 0.87554, "counts": 4215}, "194400": {"idx": 108, "max": 0.46218, "counts": 3942}, "196200": {"idx": 109, "max": 0.50938, "counts": 3513}, "198000": {"idx": 110, "max": 0.37973, "counts": 3213}, "199800": {"idx": 111, "max": 0.50106, "counts": 3003}, "201600": {"idx": 112, "max": 0.31157, "counts": 2767}, "203400": {"idx": 113, "max": 0.28319, "counts": 2652}, "205200": {"idx": 114, "max": 0.3048, "counts": 2499}, "207000": {"idx": 115, "max": 0.32208, "counts": 2454}, "208800": {"idx": 116, "max": 0.31408, "counts": 2482}, "210600": {"idx": 117, "max": 0.35766, "counts": 2437}, "212400": {"idx": 118, "max": 0.44919, "counts": 2424}, "214200": {"idx": 119, "max": 0.41727, "counts": 2356}, "216000": {"idx": 120, "max": 0.3502, "counts": 2322}, "217800": {"idx": 121, "max": 0.44414, "counts": 2140}, "219600": {"idx": 122, "max": 0.46887, "counts": 2262}, "221400": {"idx": 123, "max": 0.56257, "counts": 2603}, "223200": {"idx": 124, "max": 0.52626, "counts": 2713}, "225000": {"idx": 125, "max": 0.54572, "counts": 2743}, "226800": {"idx": 126, "max": 0.47303, "counts": 2878}, "228600": {"idx": 127, "max": 0.45365, "counts": 3214}, "230400": {"idx": 128, "max": 0.65088, "counts": 3388}, "232200": {"idx": 129, "max": 0.78115, "counts": 3276}, "234000": {"idx": 130, "max": 0.86305, "counts": 3815}, "235800": {"idx": 131, "max": 0.84348, "counts": 4178}, "237600": {"idx": 132, "max": 1.50616, "counts": 4863}, "239400": {"idx": 133, "max": 1.3852, "counts": 5304}, "241200": {"idx": 134, "max": 1.68858, "counts": 5735}, "243000": {"idx": 135, "max": 2.14544, "counts": 5662}, "244800": {"idx": 136, "max": 2.65536, "counts": 5230}, "246600": {"idx": 137, "max": 0.95205, "counts": 4799}, "248400": {"idx": 138, "max": 1.89482, "counts": 4861}, "250200": {"idx": 139, "max": 2.13694, "counts": 5009}, "252000": {"idx": 140, "max": 2.23648, "counts": 5135}, "253800": {"idx": 141, "max": 1.99603, "counts": 5569}, "255600": {"idx": 142, "max": 2.46551, "counts": 5063}, "257400": {"idx": 143, "max": 1.43896, "counts": 4638}, "259200": {"idx": 144, "max": 0.0, "counts": 0}}}