{"39": {"0": {"idx": 0, "max": 0.02987, "counts": 82}, "1800": {"idx": 1, "max": 0.03773, "counts": 201}, "3600": {"idx": 2, "max": 0.03971, "counts": 323}, "5400": {"idx": 3, "max": 0.04389, "counts": 496}, "7200": {"idx": 4, "max": 0.06303, "counts": 658}, "9000": {"idx": 5, "max": 0.0934, "counts": 813}, "10800": {"idx": 6, "max": 0.07544, "counts": 894}, "12600": {"idx": 7, "max": 0.08708, "counts": 930}, "14400": {"idx": 8, "max": 0.12378, "counts": 748}, "16200": {"idx": 9, "max": 0.07558, "counts": 638}, "18000": {"idx": 10, "max": 0.07271, "counts": 611}, "19800": {"idx": 11, "max": 0.14042, "counts": 730}, "21600": {"idx": 12, "max": 0.10308, "counts": 968}, "23400": {"idx": 13, "max": 0.08196, "counts": 899}, "25200": {"idx": 14, "max": 0.08902, "counts": 652}, "27000": {"idx": 15, "max": 0.04899, "counts": 557}, "28800": {"idx": 16, "max": 0.05493, "counts": 478}, "30600": {"idx": 17, "max": 0.06673, "counts": 518}, "32400": {"idx": 18, "max": 0.05147, "counts": 509}, "34200": {"idx": 19, "max": 0.11532, "counts": 534}, "36000": {"idx": 20, "max": 0.07023, "counts": 318}, "37800": {"idx": 21, "max": 0.03723, "counts": 318}, "39600": {"idx": 22, "max": 0.03142, "counts": 315}, "41400": {"idx": 23, "max": 0.03778, "counts": 332}, "43200": {"idx": 24, "max": 0.03146, "counts": 344}, "45000": {"idx": 25, "max": 0.0389, "counts": 447}, "46800": {"idx": 26, "max": 0.06297, "counts": 513}, "48600": {"idx": 27, "max": 0.08267, "counts": 512}, "50400": {"idx": 28, "max": 0.10722, "counts": 580}, "52200": {"idx": 29, "max": 0.11891, "counts": 558}, "54000": {"idx": 30, "max": 0.19166, "counts": 646}, "55800": {"idx": 31, "max": 0.17425, "counts": 702}, "57600": {"idx": 32, "max": 0.1908, "counts": 773}, "59400": {"idx": 33, "max": 0.25796, "counts": 837}, "61200": {"idx": 34, "max": 0.23465, "counts": 857}, "63000": {"idx": 35, "max": 0.3752, "counts": 998}, "64800": {"idx": 36, "max": 0.46384, "counts": 1093}, "66600": {"idx": 37, "max": 0.3893, "counts": 1174}, "68400": {"idx": 38, "max": 0.54137, "counts": 1213}, "70200": {"idx": 39, "max": 0.63293, "counts": 1293}, "72000": {"idx": 40, "max": 0.38614, "counts": 1310}, "73800": {"idx": 41, "max": 0.48046, "counts": 1323}, "75600": {"idx": 42, "max": 0.36782, "counts": 1378}, "77400": {"idx": 43, "max": 0.4477, "counts": 1459}, "79200": {"idx": 44, "max": 0.4282, "counts": 1582}, "81000": {"idx": 45, "max": 0.47656, "counts": 1714}, "82800": {"idx": 46, "max": 0.60806, "counts": 1799}, "84600": {"idx": 47, "max": 0.61168, "counts": 1879}, "86400": {"idx": 48, "max": 0.70004, "counts": 1922}, "88200": {"idx": 49, "max": 0.73862, "counts": 1979}, "90000": {"idx": 50, "max": 0.69743, "counts": 2045}, "91800": {"idx": 51, "max": 0.49437, "counts": 2067}, "93600": {"idx": 52, "max": 0.3871, "counts": 2085}, "95400": {"idx": 53, "max": 0.50643, "counts": 2186}, "97200": {"idx": 54, "max": 0.50203, "counts": 2235}, "99000": {"idx": 55, "max": 0.64552, "counts": 2399}, "100800": {"idx": 56, "max": 0.96798, "counts": 2528}, "102600": {"idx": 57, "max": 1.71449, "counts": 4076}, "104400": {"idx": 58, "max": 1.60094, "counts": 4531}, "106200": {"idx": 59, "max": 1.97667, "counts": 4515}, "108000": {"idx": 60, "max": 1.67721, "counts": 4315}, "109800": {"idx": 61, "max": 1.64533, "counts": 4012}, "111600": {"idx": 62, "max": 1.62118, "counts": 3910}, "113400": {"idx": 63, "max": 1.6157, "counts": 3762}, "115200": {"idx": 64, "max": 1.24536, "counts": 3319}, "117000": {"idx": 65, "max": 0.96993, "counts": 2988}, "118800": {"idx": 66, "max": 0.65408, "counts": 2708}, "120600": {"idx": 67, "max": 0.59952, "counts": 2652}, "122400": {"idx": 68, "max": 0.49883, "counts": 2249}, "124200": {"idx": 69, "max": 2.13472, "counts": 2993}, "126000": {"idx": 70, "max": 1.92081, "counts": 3843}, "127800": {"idx": 71, "max": 1.5802, "counts": 3666}, "129600": {"idx": 72, "max": 1.20375, "counts": 3168}, "131400": {"idx": 73, "max": 0.69907, "counts": 2833}, "133200": {"idx": 74, "max": 0.71939, "counts": 2525}, "135000": {"idx": 75, "max": 0.59394, "counts": 2371}, "136800": {"idx": 76, "max": 0.475, "counts": 2294}, "138600": {"idx": 77, "max": 0.271, "counts": 2197}, "140400": {"idx": 78, "max": 0.24569, "counts": 2398}, "142200": {"idx": 79, "max": 0.24974, "counts": 2245}, "144000": {"idx": 80, "max": 0.36969, "counts": 2293}, "145800": {"idx": 81, "max": 0.34686, "counts": 2447}, "147600": {"idx": 82, "max": 0.34737, "counts": 2569}, "149400": {"idx": 83, "max": 0.27499, "counts": 2567}, "151200": {"idx": 84, "max": 0.31831, "counts": 2543}, "153000": {"idx": 85, "max": 0.39539, "counts": 2723}, "154800": {"idx": 86, "max": 0.52677, "counts": 2750}, "156600": {"idx": 87, "max": 0.52712, "counts": 2768}, "158400": {"idx": 88, "max": 0.52336, "counts": 2967}, "160200": {"idx": 89, "max": 0.47384, "counts": 2998}, "162000": {"idx": 90, "max": 0.6272, "counts": 3036}, "163800": {"idx": 91, "max": 0.49007, "counts": 3090}, "165600": {"idx": 92, "max": 0.60961, "counts": 3181}, "167400": {"idx": 93, "max": 0.64258, "counts": 3262}, "169200": {"idx": 94, "max": 0.51937, "counts": 3282}, "171000": {"idx": 95, "max": 0.77165, "counts": 3477}, "172800": {"idx": 96, "max": 0.69993, "counts": 3216}, "174600": {"idx": 97, "max": 0.53481, "counts": 3228}, "176400": {"idx": 98, "max": 0.69382, "counts": 3291}, "178200": {"idx": 99, "max": 0.67542, "counts": 3488}, "180000": {"idx": 100, "max": 0.57713, "counts": 3600}, "181800": {"idx": 101, "max": 0.57055, "counts": 3332}, "183600": {"idx": 102, "max": 0.50303, "counts": 3345}, "185400": {"idx": 103, "max": 0.4085, "counts": 2927}, "187200": {"idx": 104, "max": 0.35249, "counts": 3138}, "189000": {"idx": 105, "max": 0.46348, "counts": 3118}, "190800": {"idx": 106, "max": 0.26207, "counts": 3021}, "192600": {"idx": 107, "max": 0.26299, "counts": 2953}, "194400": {"idx": 108, "max": 0.2843, "counts": 2785}, "196200": {"idx": 109, "max": 0.27404, "counts": 2588}, "198000": {"idx": 110, "max": 0.29963, "counts": 2374}, "199800": {"idx": 111, "max": 0.27818, "counts": 2329}, "201600": {"idx": 112, "max": 0.29142, "counts": 2186}, "203400": {"idx": 113, "max": 0.23179, "counts": 2202}, "205200": {"idx": 114, "max": 0.27943, "counts": 2096}, "207000": {"idx": 115, "max": 0.25889, "counts": 2050}, "208800": {"idx": 116, "max": 0.20637, "counts": 1860}, "210600": {"idx": 117, "max": 0.29305, "counts": 1930}, "212400": {"idx": 118, "max": 1.04935, "counts": 2536}, "214200": {"idx": 119, "max": 2.74729, "counts": 3211}, "216000": {"idx": 120, "max": 1.80991, "counts": 3728}, "217800": {"idx": 121, "max": 1.50196, "counts": 3212}, "219600": {"idx": 122, "max": 1.11506, "counts": 2893}, "221400": {"idx": 123, "max": 0.94999, "counts": 2717}, "223200": {"idx": 124, "max": 1.29828, "counts": 2563}, "225000": {"idx": 125, "max": 1.45388, "counts": 2628}, "226800": {"idx": 126, "max": 1.75996, "counts": 2660}, "228600": {"idx": 127, "max": 1.56558, "counts": 2875}, "230400": {"idx": 128, "max": 2.31296, "counts": 3123}, "232200": {"idx": 129, "max": 2.35423, "counts": 3322}, "234000": {"idx": 130, "max": 2.71292, "counts": 3280}, "235800": {"idx": 131, "max": 2.81918, "counts": 3109}, "237600": {"idx": 132, "max": 2.64325, "counts": 3233}, "239400": {"idx": 133, "max": 2.36833, "counts": 3346}, "241200": {"idx": 134, "max": 1.87129, "counts": 3522}, "243000": {"idx": 135, "max": 1.96195, "counts": 3645}, "244800": {"idx": 136, "max": 1.80754, "counts": 3691}, "246600": {"idx": 137, "max": 1.44194, "counts": 3768}, "248400": {"idx": 138, "max": 1.53177, "counts": 3859}, "250200": {"idx": 139, "max": 2.14396, "counts": 3970}, "252000": {"idx": 140, "max": 3.3335, "counts": 3901}, "253800": {"idx": 141, "max": 3.53659, "counts": 3686}, "255600": {"idx": 142, "max": 3.51273, "counts": 3472}, "257400": {"idx": 143, "max": 3.10051, "counts": 3123}, "259200": {"idx": 144, "max": 0.0, "counts": 0}}}